MANIFEST.in
README.md
requirements.txt
setup.py
kdezero/__init__.py
kdezero/core.py
kdezero/cuda.py
kdezero/dataloaders.py
kdezero/layers.py
kdezero/logger.py
kdezero/models.py
kdezero/optimizers.py
kdezero/transforms.py
kdezero.egg-info/PKG-INFO
kdezero.egg-info/SOURCES.txt
kdezero.egg-info/dependency_links.txt
kdezero.egg-info/requires.txt
kdezero.egg-info/top_level.txt
kdezero/datasets/__init__.py
kdezero/datasets/core.py
kdezero/datasets/imagenet.py
kdezero/datasets/mnist.py
kdezero/datasets/sincurve.py
kdezero/datasets/spiral.py
kdezero/functions/__init__.py
kdezero/functions/activation_functions.py
kdezero/functions/basic_calc_functions.py
kdezero/functions/conv_functions.py
kdezero/functions/loss_functions.py
kdezero/functions/mathematical_functions.py
kdezero/functions/metrics.py
kdezero/functions/ndarray_functions.py
kdezero/functions/utils.py
kdezero/utils/__init__.py
kdezero/utils/calculation_graph.py
kdezero/utils/download_file.py
kdezero/utils/numpy_utility.py
kdezero/utils/utils.py