Metadata-Version: 2.1
Name: kdezero
Version: 2.1
Summary: This library is an my improved version of "Deep Learning from Basic 3".
Home-page: https://github.com/kotabrog/K_DeZero.git
Author: Kota Suzuki
Author-email: suzuki.kota0331@gmail.com
License: MIT
Platform: UNKNOWN
